yubetsu_cite/__init__.py
yubetsu_cite/main.py
yubetsu_cite-1.0.0.dist-info/LICENSE
yubetsu_cite-1.0.0.dist-info/METADATA
yubetsu_cite-1.0.0.dist-info/WHEEL
yubetsu_cite-1.0.0.dist-info/top_level.txt
yubetsu_cite-1.0.0.dist-info/RECORD
