Metadata-Version: 2.1
Name: yubetsu_cite
Version: 1.0.0
Summary: Yubetsu Cite is a Python tool that simplifies the generation of academic citations in various formats.
Home-page: https://github.com/yubetsu/yubetsu-cite-python
Author: Yubetsu
Author-email: info@yubetsu.com
Classifier: Programming Language :: Python :: 3
Classifier: License :: OSI Approved :: Apache Software License
Classifier: Operating System :: OS Independent
Requires-Python: >=3.6
License-File: LICENSE
